[
    {
        "DOI": "10.1002/essoar.95a79bd46e3a0342.6bebb835b5a94839.1",
        "URL": "http://dx.doi.org/10.1002/essoar.95a79bd46e3a0342.6bebb835b5a94839.1",
        "author": [
            {
                "ORCID": "http://orcid.org/0000-0003-2993-8687",
                "affiliation": [
                    {
                        "name": "University of British Columbia Institute for Resources Environment and Sustainability"
                    }
                ],
                "authenticated-orcid": false,
                "family": "Kim",
                "given": "Yeonuk",
                "sequence": "first"
            },
            {
                "ORCID": "http://orcid.org/0000-0001-5070-7539",
                "affiliation": [
                    {
                        "name": "University of British Columbia Department of Earth and Ocean Sciences"
                    },
                    {
                        "name": "University of British Columbia Institute for Resources Environment and Sustainability"
                    }
                ],
                "authenticated-orcid": false,
                "family": "Johnson",
                "given": "Mark",
                "sequence": "additional"
            }
        ],
        "content-domain": {
            "crossmark-restriction": false,
            "domain": []
        },
        "created": {
            "date-parts": [
                [
                    2019,
                    11,
                    13
                ]
            ],
            "date-time": "2019-11-13T09:32:58Z",
            "timestamp": 1573637578000
        },
        "deposited": {
            "date-parts": [
                [
                    2021,
                    2,
                    23
                ]
            ],
            "date-time": "2021-02-23T13:59:20Z",
            "timestamp": 1614088760000
        },
        "funder": [
            {
                "DOI": "10.13039/501100000038",
                "award": [
                    "WTWPJ 506082-2016"
                ],
                "doi-asserted-by": "publisher",
                "name": "Natural Sciences and Engineering Research Council of Canada"
            }
        ],
        "group-title": "Hydrology",
        "indexed": {
            "date-parts": [
                [
                    2021,
                    2,
                    23
                ]
            ],
            "date-time": "2021-02-23T15:05:44Z",
            "timestamp": 1614092744878
        },
        "institution": {
            "acronym": [
                "ESSOAr"
            ],
            "name": "Earth and Space Science Open Archive",
            "place": [
                "-"
            ]
        },
        "is-referenced-by-count": 0,
        "issued": {
            "date-parts": [
                [
                    2018,
                    3,
                    10
                ]
            ]
        },
        "link": [
            {
                "URL": "https://www.essoar.org/pdfjs/10.1002/essoar.95a79bd46e3a0342.6bebb835b5a94839.1",
                "content-type": "unspecified",
                "content-version": "vor",
                "intended-application": "similarity-checking"
            }
        ],
        "member": "311",
        "posted": {
            "date-parts": [
                [
                    2018,
                    3,
                    10
                ]
            ]
        },
        "prefix": "10.1002",
        "publisher": "Wiley",
        "reference": [
            {
                "key": "p_1",
                "unstructured": "Narasimhan B. and R. Srinivasan (2005). \"Development and evaluation of"
            },
            {
                "key": "p_2",
                "unstructured": "Soil Moisture Deficit Index (SMDI) and Evapotranspiration Deficit Index (ETDI)"
            },
            {
                "key": "p_3",
                "unstructured": "for agricultural drought monitoring.\" Agricultural and forest meteorology 133(1)\n  :"
            },
            {
                "key": "p_4",
                "unstructured": "69-88."
            },
            {
                "DOI": "10.1111/gcb.13389",
                "doi-asserted-by": "crossref",
                "key": "p_5",
                "unstructured": "Konings A. G. and P. Gentine (2016). \"Global Variations in Ecosystem-Scale"
            },
            {
                "key": "p_6",
                "unstructured": "Isohydricity.\" Global Change Biology"
            },
            {
                "key": "p_7",
                "unstructured": "Ning Z. etal (2008). \"Causes and impacts of the 2005 Amazon drought.\""
            },
            {
                "key": "p_8",
                "unstructured": "Environmental Research Letters 3 1"
            },
            {
                "key": "p_9",
                "unstructured": "Stoy P. C. etal (2005). \"Variability in net ecosystem exchange from hourly"
            },
            {
                "key": "p_10",
                "unstructured": "to inter-annual time scales at adjacent pine and hardwood forests: a wavelet"
            },
            {
                "DOI": "10.1093/treephys/25.7.887",
                "doi-asserted-by": "crossref",
                "first-page": "887",
                "issue": "7",
                "journal-title": "Tree Physiol",
                "key": "p_11",
                "volume": "25"
            },
            {
                "key": "p_12",
                "unstructured": "Zaccarelli N. etal (2013). \"Order and disorder in ecological time-series:"
            },
            {
                "author": "Introducing",
                "first-page": "22",
                "journal-title": "Ecological Indicators",
                "key": "p_13",
                "volume": "28"
            },
            {
                "DOI": "10.1016/j.rse.2017.06.031",
                "doi-asserted-by": "crossref",
                "key": "p_14",
                "unstructured": "Gorelick N. etal (2017). \"Google Earth Engine: Planetary-scale geospatial"
            },
            {
                "key": "p_15",
                "unstructured": "analysis for everyone.\" Remote Sensing of Environment."
            },
            {
                "DOI": "10.3133/ds832",
                "doi-asserted-by": "crossref",
                "key": "p_16",
                "unstructured": "Funk C.C. etal (2014). \"A quasi-global precipitation time series for drought"
            },
            {
                "key": "p_17",
                "unstructured": "monitoring.\" U.S. Geological Survey Data Series 832 4."
            },
            {
                "key": "p_18",
                "unstructured": "Hunt E. R. and B. N. Rock (1989). \"Detection of changes in leaf water"
            },
            {
                "key": "p_19",
                "unstructured": "content using Near- and Middle-Infrared reflectances.\" Remote Sensing of"
            },
            {
                "first-page": "43",
                "issue": "1",
                "journal-title": "Environment",
                "key": "p_20",
                "volume": "30"
            },
            {
                "key": "p_21",
                "unstructured": "Inman-Bamber N. G. and D. M. Smith (2005). \"Water relations in sugarcane"
            },
            {
                "first-page": "185",
                "issue": "2",
                "journal-title": "Field Crops Research",
                "key": "p_22",
                "volume": "92"
            }
        ],
        "reference-count": 22,
        "references-count": 22,
        "relation": {
            "cites": []
        },
        "score": 28.865181,
        "source": "Crossref",
        "subtype": "other",
        "title": [
            "Spectral entropy as a mean to quantify water stress history for natural vegetation and irrigated agriculture in a water-stressed tropical environment"
        ],
        "type": "posted-content"
    },
    {
        "DOI": "10.1175/2012ei000439.1",
        "ISSN": [
            "1087-3562"
        ],
        "URL": "http://dx.doi.org/10.1175/2012ei000439.1",
        "abstract": "<jats:title>Abstract</jats:title>\n               <jats:p>Tropical Africa is affected by intense land-use change, particularly forest conversion to agricultural land. In this study, the stream discharge of four small headwater catchments located within an area of 6 km2 in western Kenya was examined for 2 years (2007 and 2008). The four catchments cover a degradation gradient ranging from intact forest to agricultural land under maize cultivation for 5, 10, and 50 years. The runoff ratio (e.g., annual catchment discharge expressed as a percentage of rainfall) increased with increasing duration of cultivation from an average of 16.0% in the forest to 32.4% in the 50-yr-old agricultural catchment. Similarly, the average runoff ratio due to the stormflow component was 0.033 in the forest and increased gradually to 0.095 with increasing duration of cultivation. The conversion from forest to agricultural land in the first 5 years caused about half of the total observed increases in runoff ratio (46.3%) and discharge in relation to rainfall (50.6%). The other half of the changes in discharge occurred later during soil degradation after forest clearing. With increasing duration of cultivation, soil bulk density \u03c1b at a depth of 0\u20130.1 m increased by 46%, while soil organic carbon (SOC) concentrations and total porosity decreased by 75% and 20%, respectively. The changes in hydrological responses that occurred in the initial years after forest clearing may suggest a significant potential for improved land management in alleviating runoff and enhanced storm flow and moisture retention in agricultural watersheds.</jats:p>",
        "author": [
            {
                "affiliation": [
                    {
                        "name": "Department of Crop and Soil Sciences, Cornell University, Ithaca, New York"
                    }
                ],
                "family": "Recha",
                "given": "John W.",
                "sequence": "first"
            },
            {
                "affiliation": [
                    {
                        "name": "Department of Crop and Soil Sciences, Cornell University, Ithaca, New York"
                    }
                ],
                "family": "Lehmann",
                "given": "Johannes",
                "sequence": "first"
            },
            {
                "affiliation": [
                    {
                        "name": "Department of Biological and Environmental Engineering, Cornell University, Ithaca, New York"
                    }
                ],
                "family": "Walter",
                "given": "M. Todd",
                "sequence": "additional"
            },
            {
                "affiliation": [
                    {
                        "name": "Department of Animal Sciences, Cornell University, Ithaca, New York"
                    }
                ],
                "family": "Pell",
                "given": "Alice",
                "sequence": "additional"
            },
            {
                "affiliation": [
                    {
                        "name": "Center for International Forestry Research, Bogor, Indonesia"
                    }
                ],
                "family": "Verchot",
                "given": "Louis",
                "sequence": "additional"
            },
            {
                "affiliation": [
                    {
                        "name": "Institute for Resources, Environment and Sustainability, and Department of Earth and Ocean Sciences, University of British Columbia, Vancouver, British Columbia, Canada"
                    }
                ],
                "family": "Johnson",
                "given": "Mark",
                "sequence": "additional"
            }
        ],
        "container-title": [
            "Earth Interactions"
        ],
        "content-domain": {
            "crossmark-restriction": false,
            "domain": []
        },
        "created": {
            "date-parts": [
                [
                    2012,
                    8,
                    10
                ]
            ],
            "date-time": "2012-08-10T20:37:18Z",
            "timestamp": 1344631038000
        },
        "deposited": {
            "date-parts": [
                [
                    2021,
                    1,
                    5
                ]
            ],
            "date-time": "2021-01-05T16:59:07Z",
            "timestamp": 1609865947000
        },
        "indexed": {
            "date-parts": [
                [
                    2021,
                    2,
                    23
                ]
            ],
            "date-time": "2021-02-23T05:36:14Z",
            "timestamp": 1614058574992
        },
        "is-referenced-by-count": 34,
        "issn-type": [
            {
                "type": "electronic",
                "value": "1087-3562"
            }
        ],
        "issue": "13",
        "issued": {
            "date-parts": [
                [
                    2012,
                    12,
                    1
                ]
            ]
        },
        "journal-issue": {
            "issue": "13",
            "published-print": {
                "date-parts": [
                    [
                        2012,
                        12,
                        1
                    ]
                ]
            }
        },
        "language": "en",
        "link": [
            {
                "URL": "http://journals.ametsoc.org/ei/article-pdf/16/13/1/4098011/2012ei000439_1.pdf",
                "content-type": "application/pdf",
                "content-version": "vor",
                "intended-application": "syndication"
            },
            {
                "URL": "http://journals.ametsoc.org/ei/article-pdf/16/13/1/4098011/2012ei000439_1.pdf",
                "content-type": "unspecified",
                "content-version": "vor",
                "intended-application": "similarity-checking"
            }
        ],
        "member": "12",
        "page": "1-18",
        "prefix": "10.1175",
        "published-online": {
            "date-parts": [
                [
                    2012,
                    12,
                    10
                ]
            ]
        },
        "published-print": {
            "date-parts": [
                [
                    2012,
                    12,
                    1
                ]
            ]
        },
        "publisher": "American Meteorological Society",
        "reference": [
            {
                "article-title": "Contribution of earthworms to porosity and water infiltration in a tropical soil under forest and long-term cultivation",
                "author": "Aina",
                "first-page": "131",
                "journal-title": "Pedobiologia",
                "key": "2020061014110200800_bib1",
                "volume": "26",
                "year": "1984"
            },
            {
                "DOI": "10.1016/j.agee.2008.04.012",
                "article-title": "Dynamics of topsoil carbon and nitrogen along a tropical forest\u2013cropland chronosequence: Evidence from stable isotope analysis and spectroscopy",
                "author": "Awiti",
                "doi-asserted-by": "crossref",
                "first-page": "265",
                "journal-title": "Agric. Ecosyst. Environ.",
                "key": "2020061014110200800_bib2",
                "volume": "127",
                "year": "2008"
            },
            {
                "DOI": "10.1111/j.1752-1688.2004.tb01046.x",
                "article-title": "A new flashiness index: Characteristics and applications to Midwestern rivers and streams",
                "author": "Baker",
                "doi-asserted-by": "crossref",
                "first-page": "503",
                "journal-title": "J. Amer. Water Resour. Assoc.",
                "key": "2020061014110200800_bib3",
                "volume": "40",
                "year": "2004"
            },
            {
                "DOI": "10.1016/S0022-1694(01)00383-3",
                "article-title": "Basin hydrologic response relations to distributed physiographic descriptors and climate",
                "author": "Berger",
                "doi-asserted-by": "crossref",
                "first-page": "169",
                "journal-title": "J. Hydrol.",
                "key": "2020061014110200800_bib4",
                "volume": "247",
                "year": "2001"
            },
            {
                "DOI": "10.1007/s10531-004-3509-3",
                "article-title": "Assessment of threat status and management effectiveness in Kakamega forest, Kenya",
                "author": "Bleher",
                "doi-asserted-by": "crossref",
                "first-page": "1159",
                "journal-title": "Biodiversity Conserv.",
                "key": "2020061014110200800_bib5",
                "volume": "15",
                "year": "2006"
            },
            {
                "DOI": "10.1016/j.jhydrol.2009.04.025",
                "article-title": "Examining geological controls on baseflow index (BFI) using regression analysis: An illustration from the Thames Basin, UK",
                "author": "Bloomfield",
                "doi-asserted-by": "crossref",
                "first-page": "164",
                "journal-title": "J. Hydrol.",
                "key": "2020061014110200800_bib6",
                "volume": "373",
                "year": "2009"
            },
            {
                "author": "Bonell",
                "key": "2020061014110200800_bib7",
                "year": "1993"
            },
            {
                "DOI": "10.1016/0022-1694(82)90117-2",
                "article-title": "A review of catchment experiments to determine the effect of vegetation changes on water yield and evapotranspiration",
                "author": "Bosch",
                "doi-asserted-by": "crossref",
                "first-page": "3",
                "journal-title": "J. Hydrol.",
                "key": "2020061014110200800_bib8",
                "volume": "55",
                "year": "1982"
            },
            {
                "author": "Bruijnzeel",
                "key": "2020061014110200800_bib9",
                "year": "1990"
            },
            {
                "DOI": "10.1016/j.agee.2004.01.015",
                "article-title": "Hydrological functions of tropical forests: Not seeing the soil for the trees?",
                "author": "Bruijnzeel",
                "doi-asserted-by": "crossref",
                "first-page": "185",
                "journal-title": "Agric. Ecosyst. Environ.",
                "key": "2020061014110200800_bib10",
                "volume": "104",
                "year": "2004"
            },
            {
                "author": "Bruijnzeel",
                "key": "2020061014110200800_bib11",
                "year": "2004"
            },
            {
                "DOI": "10.1093/treephys/18.8-9.625",
                "article-title": "Water use by forests, limits and controls",
                "author": "Calder",
                "doi-asserted-by": "crossref",
                "first-page": "625",
                "journal-title": "Tree Physiol.",
                "key": "2020061014110200800_bib12",
                "volume": "18",
                "year": "1998"
            },
            {
                "author": "Campbell",
                "key": "2020061014110200800_bib13",
                "year": "1991"
            },
            {
                "DOI": "10.1016/0022-1694(93)90235-2",
                "article-title": "Hydrological processes in a small humid savanna basin",
                "author": "Chevallier",
                "doi-asserted-by": "crossref",
                "first-page": "173",
                "journal-title": "J. Hydrol.",
                "key": "2020061014110200800_bib14",
                "volume": "151",
                "year": "1993"
            },
            {
                "DOI": "10.1016/S0022-1694(03)00267-1",
                "article-title": "Effects of large-scale changes in land cover on the discharge of the Tocantins River, Amazonia",
                "author": "Costa",
                "doi-asserted-by": "crossref",
                "first-page": "206",
                "journal-title": "J. Hydrol.",
                "key": "2020061014110200800_bib15",
                "volume": "283",
                "year": "2003"
            },
            {
                "DOI": "10.1016/j.geoderma.2009.10.001",
                "article-title": "Rapid erosion modeling in a western Kenya watershed using near infrared reflectance, classification tree analysis and 137Cesium",
                "author": "deGraffenried",
                "doi-asserted-by": "crossref",
                "first-page": "93",
                "journal-title": "Geoderma",
                "key": "2020061014110200800_bib16",
                "volume": "154",
                "year": "2009"
            },
            {
                "author": "Edwards",
                "key": "2020061014110200800_bib17",
                "year": "1996"
            },
            {
                "DOI": "10.1080/00128325.1979.11662947",
                "article-title": "Soil moisture deficits under montane rain forest and tea",
                "author": "Eeles",
                "doi-asserted-by": "crossref",
                "first-page": "128",
                "journal-title": "East Afr. Agric. For. J.",
                "key": "2020061014110200800_bib18",
                "volume": "43",
                "year": "1979"
            },
            {
                "DOI": "10.1002/hyp.237",
                "article-title": "Hydrologic flowpaths in tropical rainforest soilscapes\u2014A review",
                "author": "Elsenbeer",
                "doi-asserted-by": "crossref",
                "first-page": "1751",
                "journal-title": "Hydrol. Processes",
                "key": "2020061014110200800_bib19",
                "volume": "15",
                "year": "2001"
            },
            {
                "key": "2020061014110200800_bib20",
                "unstructured": "FAO, cited 2010: Global forest resources assessment 2005. Food and Agriculture Organization of the United Nations. [Available online at http://www.fao.org/forestry/site/countryinfo/en/ken.]"
            },
            {
                "author": "FAO-UNESCO-ISRIC",
                "key": "2020061014110200800_bib21",
                "year": "1988"
            },
            {
                "DOI": "10.1111/j.1365-2486.2005.01011.x",
                "article-title": "Effects of afforestation on water yield: A global synthesis with implications for policy",
                "author": "Farley",
                "doi-asserted-by": "crossref",
                "first-page": "1565",
                "journal-title": "Global Change Biol.",
                "key": "2020061014110200800_bib22",
                "volume": "11",
                "year": "2005"
            },
            {
                "article-title": "The hydrological effects of clearing tropical rain forest and of the implementation of alternative land uses",
                "author": "Fritsch",
                "first-page": "53",
                "key": "2020061014110200800_bib23",
                "year": "1993"
            },
            {
                "DOI": "10.5194/hess-10-383-2006",
                "article-title": "Throughfall and temporal trends of rainfall redistribution in an open tropical rainforest, south-western Amazonia (Rond\u00f4nia, Brazil)",
                "author": "Germer",
                "doi-asserted-by": "crossref",
                "first-page": "383",
                "journal-title": "Hydrol. Earth Syst. Sci.",
                "key": "2020061014110200800_bib24",
                "volume": "10",
                "year": "2006"
            },
            {
                "DOI": "10.1016/j.jhydrol.2009.11.022",
                "article-title": "Influence of land use change on near surface hydrological processes: Undisturbed forest to pasture",
                "author": "Germer",
                "doi-asserted-by": "crossref",
                "first-page": "473",
                "journal-title": "J. Hydrol.",
                "key": "2020061014110200800_bib25",
                "volume": "380",
                "year": "2010"
            },
            {
                "DOI": "10.1016/j.pce.2003.09.009",
                "article-title": "Analysis of the hydrological processes in a small headwater catchment in Benin (West Africa)",
                "author": "Giertz",
                "doi-asserted-by": "crossref",
                "first-page": "1333",
                "journal-title": "Phys. Chem. Earth",
                "key": "2020061014110200800_bib26",
                "volume": "28",
                "year": "2003"
            },
            {
                "DOI": "10.1016/j.pce.2005.07.003",
                "article-title": "Assessing the effects of land use change on soil physical properties and hydrological processes in the sub-humid tropical environment of West Africa",
                "author": "Giertz",
                "doi-asserted-by": "crossref",
                "first-page": "485",
                "journal-title": "Phys. Chem. Earth",
                "key": "2020061014110200800_bib27",
                "volume": "30",
                "year": "2005"
            },
            {
                "DOI": "10.2307/3673199",
                "article-title": "The effects of forestation on soil hydraulic properties in the Middle Hills of Nepal: A preliminary assessment",
                "author": "Gilmour",
                "doi-asserted-by": "crossref",
                "first-page": "239",
                "journal-title": "Mt. Res. Dev.",
                "key": "2020061014110200800_bib28",
                "volume": "7",
                "year": "1987"
            },
            {
                "DOI": "10.1016/j.foreco.2006.08.014",
                "article-title": "Carbon storage and emissions offset potential in an East African tropical rainforest",
                "author": "Glenday",
                "doi-asserted-by": "crossref",
                "first-page": "72",
                "journal-title": "For. Ecol. Manage.",
                "key": "2020061014110200800_bib29",
                "volume": "235",
                "year": "2006"
            },
            {
                "author": "Grip",
                "key": "2020061014110200800_bib30",
                "year": "2004"
            },
            {
                "article-title": "Land cover change and soil fertility decline in tropical regions",
                "author": "Hartemink",
                "first-page": "195",
                "journal-title": "Turk. J. Agric. For.",
                "key": "2020061014110200800_bib31",
                "volume": "32",
                "year": "2008"
            },
            {
                "author": "Haupt",
                "key": "2020061014110200800_bib32",
                "year": "2000"
            },
            {
                "DOI": "10.1016/j.foreco.2009.07.019",
                "article-title": "Below and above ground biomass and net primary production in a paleotropical natural forest (Sulawesi, Indonesia) as compared to neotropical forest",
                "author": "Hertel",
                "doi-asserted-by": "crossref",
                "first-page": "1904",
                "journal-title": "For. Ecol. Manage.",
                "key": "2020061014110200800_bib33",
                "volume": "258",
                "year": "2009"
            },
            {
                "DOI": "10.1016/S0341-8162(98)00053-8",
                "article-title": "Soil chronosequences, soil development, and soil evolution: A critical review",
                "author": "Huggett",
                "doi-asserted-by": "crossref",
                "first-page": "155",
                "journal-title": "Catena",
                "key": "2020061014110200800_bib34",
                "volume": "32",
                "year": "1998"
            },
            {
                "author": "J\u00e4tzold",
                "key": "2020061014110200800_bib35",
                "year": "1983"
            },
            {
                "DOI": "10.1007/s10533-006-9029-3",
                "article-title": "DOC and DIC in flowpaths of Amazonian headwater catchments with hydrologically contrasting soils",
                "author": "Johnson",
                "doi-asserted-by": "crossref",
                "first-page": "45",
                "journal-title": "Biogeochemistry",
                "key": "2020061014110200800_bib36",
                "volume": "81",
                "year": "2006"
            },
            {
                "author": "Kenya Forest Service",
                "key": "2020061014110200800_bib37",
                "year": "2007"
            },
            {
                "DOI": "10.1007/s10021-008-9154-z",
                "article-title": "Reversibility of soil productivity decline with organic matter of differing quality along a degradation gradient",
                "author": "Kimetu",
                "doi-asserted-by": "crossref",
                "first-page": "726",
                "journal-title": "Ecosystems",
                "key": "2020061014110200800_bib38",
                "volume": "11",
                "year": "2008"
            },
            {
                "DOI": "10.1016/j.soilbio.2009.07.022",
                "article-title": "Soil organic C stabilization and thresholds in C saturation",
                "author": "Kimetu",
                "doi-asserted-by": "crossref",
                "first-page": "2100",
                "journal-title": "Soil Biol. Biochem.",
                "key": "2020061014110200800_bib39",
                "volume": "41",
                "year": "2009"
            },
            {
                "key": "2020061014110200800_bib40",
                "unstructured": "Kinyangi, J. M.\n          , 2008: Soil degradation, thresholds and dynamics of long-term cultivation: From landscape biogeochemistry to nanoscale biogeocomplexity. Ph.D. dissertation, Cornell University, 158 pp."
            },
            {
                "author": "Klute",
                "key": "2020061014110200800_bib41",
                "year": "1986"
            },
            {
                "author": "Lal",
                "key": "2020061014110200800_bib42",
                "year": "1981"
            },
            {
                "author": "Lal",
                "key": "2020061014110200800_bib43",
                "year": "1983"
            },
            {
                "author": "Lal",
                "key": "2020061014110200800_bib44",
                "year": "1987"
            },
            {
                "DOI": "10.1002/(SICI)1099-145X(199603)7:1<19::AID-LDR212>3.0.CO;2-M",
                "article-title": "Deforestation and land-use effects on soil degradation and rehabilitation in western Nigeria. I. Soil physical and hydrological properties",
                "author": "Lal",
                "doi-asserted-by": "crossref",
                "first-page": "19",
                "journal-title": "Land Degrad. Dev.",
                "key": "2020061014110200800_bib45",
                "volume": "7",
                "year": "1996"
            },
            {
                "DOI": "10.1023/B:BIOG.0000015279.48813.9d",
                "article-title": "Water and element input into native, agri- and silvicultural ecosystems of the Brazilian savanna",
                "author": "Lilienfein",
                "doi-asserted-by": "crossref",
                "first-page": "183",
                "journal-title": "Biogeochemistry",
                "key": "2020061014110200800_bib46",
                "volume": "67",
                "year": "2004"
            },
            {
                "DOI": "10.1111/j.1752-1688.2005.tb03808.x",
                "article-title": "Automated Web GIS based Hydrograph Analysis Tool, WHAT",
                "author": "Lim",
                "doi-asserted-by": "crossref",
                "first-page": "1407",
                "journal-title": "J. Amer. Water Resour. Assoc.",
                "key": "2020061014110200800_bib47",
                "volume": "41",
                "year": "2005"
            },
            {
                "DOI": "10.1016/j.cageo.2010.01.004",
                "article-title": "Development of genetic algorithm-based optimization module in WHAT system for hydrograph analysis and model application",
                "author": "Lim",
                "doi-asserted-by": "crossref",
                "first-page": "936",
                "journal-title": "Comput. Geosci.",
                "key": "2020061014110200800_bib48",
                "volume": "36",
                "year": "2010"
            },
            {
                "DOI": "10.1016/j.jhydrol.2008.03.011",
                "article-title": "Baseflow index regionalization analysis in a Mediterranean area and data scarcity context: Role of catchment permeability index",
                "author": "Longobardi",
                "doi-asserted-by": "crossref",
                "first-page": "63",
                "journal-title": "J. Hydrol.",
                "key": "2020061014110200800_bib49",
                "volume": "355",
                "year": "2008"
            },
            {
                "article-title": "Water balance studies in Selangor, west Malaysia",
                "author": "Low",
                "first-page": "60",
                "journal-title": "Trop. Geogr.",
                "key": "2020061014110200800_bib50",
                "volume": "35",
                "year": "1972"
            },
            {
                "DOI": "10.1111/j.1365-2028.2006.00663.x",
                "article-title": "Assessing fragmentation and disturbance of west Kenyan rainforests by means of remotely sensed time series data and landscape metrics",
                "author": "Lung",
                "doi-asserted-by": "crossref",
                "first-page": "491",
                "journal-title": "Afr. J. Ecol.",
                "key": "2020061014110200800_bib51",
                "volume": "44",
                "year": "2006"
            },
            {
                "DOI": "10.1016/0022-1694(92)90029-U",
                "article-title": "Water yield changes after clear-felling tropical rainforest and establishment of forest plantation in Sabah, Malaysia",
                "author": "Malmer",
                "doi-asserted-by": "crossref",
                "first-page": "77",
                "journal-title": "J. Hydrol.",
                "key": "2020061014110200800_bib52",
                "volume": "134",
                "year": "1992"
            },
            {
                "DOI": "10.1016/0378-1127(90)90081-L",
                "article-title": "Soil disturbance and loss of infiltrability caused by mechanized and manual extraction of tropical rainforest in Sabah, Malaysia",
                "author": "Malmer",
                "doi-asserted-by": "crossref",
                "first-page": "1",
                "journal-title": "For. Ecol. Manage.",
                "key": "2020061014110200800_bib53",
                "volume": "38",
                "year": "1990"
            },
            {
                "author": "Mitchell",
                "key": "2020061014110200800_bib54",
                "year": "2004"
            },
            {
                "DOI": "10.1016/j.agee.2011.02.018",
                "article-title": "Long-term soil quality degradation along a cultivation chronosequence in western Kenya",
                "author": "Moebius-Clune",
                "doi-asserted-by": "crossref",
                "first-page": "86",
                "journal-title": "Agric. Ecosyst. Environ.",
                "key": "2020061014110200800_bib55",
                "volume": "141",
                "year": "2011"
            },
            {
                "DOI": "10.1016/j.foreco.2008.10.032",
                "article-title": "Forecasting hotspots of forest clearing in Kakamega Forest, western Kenya",
                "author": "Muller",
                "doi-asserted-by": "crossref",
                "first-page": "968",
                "journal-title": "For. Ecol. Manage.",
                "key": "2020061014110200800_bib56",
                "volume": "257",
                "year": "2009"
            },
            {
                "DOI": "10.1080/02626668609491073",
                "article-title": "Effect of deforestation and subsistence agriculture on runoff of the Kafue river headwaters, Zambia",
                "author": "Mumeka",
                "doi-asserted-by": "crossref",
                "first-page": "543",
                "journal-title": "Hydrol. Sci. J.",
                "key": "2020061014110200800_bib57",
                "volume": "31",
                "year": "1986"
            },
            {
                "DOI": "10.1038/372666a0",
                "article-title": "The role of deep roots in the hydrological and carbon cycles of Amazonian forests and pastures",
                "author": "Nepstad",
                "doi-asserted-by": "crossref",
                "first-page": "666",
                "journal-title": "Nature",
                "key": "2020061014110200800_bib58",
                "volume": "372",
                "year": "1994"
            },
            {
                "DOI": "10.1111/j.1365-2486.2008.01698.x",
                "article-title": "Nutrient constraints to tropical productivity in long-term degrading soils",
                "author": "Ngoze",
                "doi-asserted-by": "crossref",
                "first-page": "2810",
                "journal-title": "Global Change Biol.",
                "key": "2020061014110200800_bib59",
                "volume": "14",
                "year": "2008"
            },
            {
                "DOI": "10.1007/s10533-008-9220-9",
                "article-title": "Long-term black carbon dynamics in cultivated soil",
                "author": "Nguyen",
                "doi-asserted-by": "crossref",
                "first-page": "295",
                "journal-title": "Biogeochemistry",
                "key": "2020061014110200800_bib60",
                "volume": "89",
                "year": "2008"
            },
            {
                "DOI": "10.1016/j.jhydrol.2009.12.041",
                "article-title": "Variation of surficial soil hydraulic properties across land uses in the southern Blue Ridge Mountains",
                "author": "Price",
                "doi-asserted-by": "crossref",
                "first-page": "256",
                "journal-title": "J. Hydrol.",
                "key": "2020061014110200800_bib61",
                "volume": "383",
                "year": "2010"
            },
            {
                "DOI": "10.1029/2010WR009340",
                "article-title": "Effects of watershed land use and geomorphology on stream low flows during severe drought conditions in the southern Blue Ridge Mountains, Georgia and North Carolina, United States",
                "author": "Price",
                "doi-asserted-by": "crossref",
                "first-page": "W02516",
                "journal-title": "Water Resour. Res.",
                "key": "2020061014110200800_bib62",
                "volume": "47",
                "year": "2011"
            },
            {
                "article-title": "Soil conservation on rainfed bench terraces in upland west Java, Indonesia: Towards a new paradigm",
                "author": "Purwanto",
                "first-page": "1267",
                "journal-title": "Adv. Geoecol.",
                "key": "2020061014110200800_bib63",
                "volume": "31",
                "year": "1998"
            },
            {
                "DOI": "10.1016/0022-1694(89)90093-0",
                "article-title": "Analysis of streamflow generation following deforestation in southwest Western Australia",
                "author": "Ruprecht",
                "doi-asserted-by": "crossref",
                "first-page": "1",
                "journal-title": "J. Hydrol.",
                "key": "2020061014110200800_bib64",
                "volume": "105",
                "year": "1989"
            },
            {
                "DOI": "10.1111/j.1752-1688.2007.00130.x",
                "article-title": "Automated algorithms for heuristic base-flow separation",
                "author": "Schwartz",
                "doi-asserted-by": "crossref",
                "first-page": "1583",
                "journal-title": "J. Amer. Water Resour. Assoc.",
                "key": "2020061014110200800_bib65",
                "volume": "43",
                "year": "2007"
            },
            {
                "DOI": "10.1111/j.1365-2486.2006.01304.x",
                "article-title": "Long-term impacts of anthropogenic perturbations on dynamics and speciation of organic carbon in tropical forest and subtropical grassland ecosystems",
                "author": "Solomon",
                "doi-asserted-by": "crossref",
                "first-page": "511",
                "journal-title": "Global Change Biol.",
                "key": "2020061014110200800_bib66",
                "volume": "13",
                "year": "2007"
            },
            {
                "DOI": "10.1890/08-0095.1",
                "article-title": "Anthropogenic and climate influences on biogeochemical dynamics and molecular-level speciation of soil sulfur",
                "author": "Solomon",
                "doi-asserted-by": "crossref",
                "first-page": "989",
                "journal-title": "Ecol. Appl.",
                "key": "2020061014110200800_bib67",
                "volume": "19",
                "year": "2009"
            },
            {
                "DOI": "10.1002/hyp.3360030409",
                "article-title": "Changes in physical properties of young and old volcanic surface soils in Costa Rica after clearing of tropical rain forest",
                "author": "Spaans",
                "doi-asserted-by": "crossref",
                "first-page": "383",
                "journal-title": "Hydrol. Processes",
                "key": "2020061014110200800_bib68",
                "volume": "3",
                "year": "1989"
            },
            {
                "DOI": "10.1080/00103628409367515",
                "article-title": "A simple high sample volume ashing procedure for determination of soil organic matter",
                "author": "Storer",
                "doi-asserted-by": "crossref",
                "first-page": "759",
                "journal-title": "Commun. Soil Sci. Plant Anal.",
                "key": "2020061014110200800_bib69",
                "volume": "15",
                "year": "1984"
            },
            {
                "DOI": "10.1016/j.envsci.2008.11.003",
                "article-title": "Tradeoffs, synergies and traps among ecosystem services in the Lake Victoria basin of East Africa",
                "author": "Swallow",
                "doi-asserted-by": "crossref",
                "first-page": "504",
                "journal-title": "Environ. Sci. Policy",
                "key": "2020061014110200800_bib70",
                "volume": "12",
                "year": "2009"
            },
            {
                "DOI": "10.1029/WR023i003p00425",
                "article-title": "Reforestation and the reduction of water yield on the southern Piedmont since circa 1940",
                "author": "Trimble",
                "doi-asserted-by": "crossref",
                "first-page": "425",
                "journal-title": "Water Resour. Res.",
                "key": "2020061014110200800_bib71",
                "volume": "23",
                "year": "1987"
            },
            {
                "author": "U.S. Natural Resources Conservation Service",
                "key": "2020061014110200800_bib72",
                "year": "2003"
            },
            {
                "DOI": "10.1016/S0022-1694(01)00393-6",
                "article-title": "Modelling rainfall interception by vegetation of variable density using an adapted analytical model. Part 2. Model validation for a tropical upland mixed cropping system",
                "author": "Van Dijk",
                "doi-asserted-by": "crossref",
                "first-page": "239",
                "journal-title": "J. Hydrol.",
                "key": "2020061014110200800_bib73",
                "volume": "247",
                "year": "2001"
            },
            {
                "DOI": "10.1061/(ASCE)0733-9496(1994)120:4(485)",
                "article-title": "Flow-duration curves I: New interpretation and confidence intervals",
                "author": "Vogel",
                "doi-asserted-by": "crossref",
                "first-page": "485",
                "journal-title": "J. Water Resour. Plan. Manage.",
                "key": "2020061014110200800_bib74",
                "volume": "120",
                "year": "1994"
            },
            {
                "author": "Werner",
                "key": "2020061014110200800_bib75",
                "year": "2007"
            },
            {
                "author": "World Bank",
                "key": "2020061014110200800_bib76",
                "year": "2008"
            },
            {
                "DOI": "10.1016/S0022-1694(96)03288-X",
                "article-title": "Importance of rural roads as source areas for runoff in mountainous areas of northern Thailand",
                "author": "Ziegler",
                "doi-asserted-by": "crossref",
                "first-page": "204",
                "journal-title": "J. Hydrol.",
                "key": "2020061014110200800_bib77",
                "volume": "196",
                "year": "1997"
            },
            {
                "DOI": "10.1016/j.foreco.2005.10.070",
                "article-title": "The influence of land-use changes on soil hydraulic properties: Implications for runoff generation",
                "author": "Zimmermann",
                "doi-asserted-by": "crossref",
                "first-page": "29",
                "journal-title": "For. Ecol. Manage.",
                "key": "2020061014110200800_bib78",
                "volume": "222",
                "year": "2006"
            }
        ],
        "reference-count": 78,
        "references-count": 78,
        "relation": {
            "cites": []
        },
        "score": 19.15783,
        "source": "Crossref",
        "subject": [
            "General Earth and Planetary Sciences"
        ],
        "title": [
            "Stream Discharge in Tropical Headwater Catchments as a Result of Forest Clearing and Soil Degradation"
        ],
        "type": "journal-article",
        "volume": "16"
    },
    {
        "DOI": "10.1161/circulationaha.109.924613",
        "ISSN": [
            "0009-7322",
            "1524-4539"
        ],
        "URL": "http://dx.doi.org/10.1161/circulationaha.109.924613",
        "alternative-id": [
            "10.1161/CIRCULATIONAHA.109.924613"
        ],
        "author": [
            {
                "affiliation": [
                    {
                        "name": "From St Paul\u2019s Hospital, University of British Columbia, Vancouver, British Columbia, Canada (J.G.W., D.A.W., J.Y., R.G., J.-B.M., R.G.C., N.W., F.N., M.J., C.R.T., R.M., J.L., B.M., S.V.L., A.C.); Quebec Heart and Lung Institute, Quebec City, Quebec, Canada (J.R.-C., E.D.); Toronto General Hospital, Toronto, Ontario, Canada (M.O., E.H.); and King\u2019s College Hospital, London, UK (O.W.)."
                    }
                ],
                "family": "Webb",
                "given": "John G.",
                "sequence": "first"
            },
            {
                "affiliation": [
                    {
                        "name": "From St Paul\u2019s Hospital, University of British Columbia, Vancouver, British Columbia, Canada (J.G.W., D.A.W., J.Y., R.G., J.-B.M., R.G.C., N.W., F.N., M.J., C.R.T., R.M., J.L., B.M., S.V.L., A.C.); Quebec Heart and Lung Institute, Quebec City, Quebec, Canada (J.R.-C., E.D.); Toronto General Hospital, Toronto, Ontario, Canada (M.O., E.H.); and King\u2019s College Hospital, London, UK (O.W.)."
                    }
                ],
                "family": "Wood",
                "given": "David A.",
                "sequence": "additional"
            },
            {
                "affiliation": [
                    {
                        "name": "From St Paul\u2019s Hospital, University of British Columbia, Vancouver, British Columbia, Canada (J.G.W., D.A.W., J.Y., R.G., J.-B.M., R.G.C., N.W., F.N., M.J., C.R.T., R.M., J.L., B.M., S.V.L., A.C.); Quebec Heart and Lung Institute, Quebec City, Quebec, Canada (J.R.-C., E.D.); Toronto General Hospital, Toronto, Ontario, Canada (M.O., E.H.); and King\u2019s College Hospital, London, UK (O.W.)."
                    }
                ],
                "family": "Ye",
                "given": "Jian",
                "sequence": "additional"
            },
            {
                "affiliation": [
                    {
                        "name": "From St Paul\u2019s Hospital, University of British Columbia, Vancouver, British Columbia, Canada (J.G.W., D.A.W., J.Y., R.G., J.-B.M., R.G.C., N.W., F.N., M.J., C.R.T., R.M., J.L., B.M., S.V.L., A.C.); Quebec Heart and Lung Institute, Quebec City, Quebec, Canada (J.R.-C., E.D.); Toronto General Hospital, Toronto, Ontario, Canada (M.O., E.H.); and King\u2019s College Hospital, London, UK (O.W.)."
                    }
                ],
                "family": "Gurvitch",
                "given": "Ronen",
                "sequence": "additional"
            },
            {
                "affiliation": [
                    {
                        "name": "From St Paul\u2019s Hospital, University of British Columbia, Vancouver, British Columbia, Canada (J.G.W., D.A.W., J.Y., R.G., J.-B.M., R.G.C., N.W., F.N., M.J., C.R.T., R.M., J.L., B.M., S.V.L., A.C.); Quebec Heart and Lung Institute, Quebec City, Quebec, Canada (J.R.-C., E.D.); Toronto General Hospital, Toronto, Ontario, Canada (M.O., E.H.); and King\u2019s College Hospital, London, UK (O.W.)."
                    }
                ],
                "family": "Masson",
                "given": "Jean-Bernard",
                "sequence": "additional"
            },
            {
                "affiliation": [
                    {
                        "name": "From St Paul\u2019s Hospital, University of British Columbia, Vancouver, British Columbia, Canada (J.G.W., D.A.W., J.Y., R.G., J.-B.M., R.G.C., N.W., F.N., M.J., C.R.T., R.M., J.L., B.M., S.V.L., A.C.); Quebec Heart and Lung Institute, Quebec City, Quebec, Canada (J.R.-C., E.D.); Toronto General Hospital, Toronto, Ontario, Canada (M.O., E.H.); and King\u2019s College Hospital, London, UK (O.W.)."
                    }
                ],
                "family": "Rode\u0301s-Cabau",
                "given": "Josep",
                "sequence": "additional"
            },
            {
                "affiliation": [
                    {
                        "name": "From St Paul\u2019s Hospital, University of British Columbia, Vancouver, British Columbia, Canada (J.G.W., D.A.W., J.Y., R.G., J.-B.M., R.G.C., N.W., F.N., M.J., C.R.T., R.M., J.L., B.M., S.V.L., A.C.); Quebec Heart and Lung Institute, Quebec City, Quebec, Canada (J.R.-C., E.D.); Toronto General Hospital, Toronto, Ontario, Canada (M.O., E.H.); and King\u2019s College Hospital, London, UK (O.W.)."
                    }
                ],
                "family": "Osten",
                "given": "Mark",
                "sequence": "additional"
            },
            {
                "affiliation": [
                    {
                        "name": "From St Paul\u2019s Hospital, University of British Columbia, Vancouver, British Columbia, Canada (J.G.W., D.A.W., J.Y., R.G., J.-B.M., R.G.C., N.W., F.N., M.J., C.R.T., R.M., J.L., B.M., S.V.L., A.C.); Quebec Heart and Lung Institute, Quebec City, Quebec, Canada (J.R.-C., E.D.); Toronto General Hospital, Toronto, Ontario, Canada (M.O., E.H.); and King\u2019s College Hospital, London, UK (O.W.)."
                    }
                ],
                "family": "Horlick",
                "given": "Eric",
                "sequence": "additional"
            },
            {
                "affiliation": [
                    {
                        "name": "From St Paul\u2019s Hospital, University of British Columbia, Vancouver, British Columbia, Canada (J.G.W., D.A.W., J.Y., R.G., J.-B.M., R.G.C., N.W., F.N., M.J., C.R.T., R.M., J.L., B.M., S.V.L., A.C.); Quebec Heart and Lung Institute, Quebec City, Quebec, Canada (J.R.-C., E.D.); Toronto General Hospital, Toronto, Ontario, Canada (M.O., E.H.); and King\u2019s College Hospital, London, UK (O.W.)."
                    }
                ],
                "family": "Wendler",
                "given": "O.",
                "sequence": "additional"
            },
            {
                "affiliation": [
                    {
                        "name": "From St Paul\u2019s Hospital, University of British Columbia, Vancouver, British Columbia, Canada (J.G.W., D.A.W., J.Y., R.G., J.-B.M., R.G.C., N.W., F.N., M.J., C.R.T., R.M., J.L., B.M., S.V.L., A.C.); Quebec Heart and Lung Institute, Quebec City, Quebec, Canada (J.R.-C., E.D.); Toronto General Hospital, Toronto, Ontario, Canada (M.O., E.H.); and King\u2019s College Hospital, London, UK (O.W.)."
                    }
                ],
                "family": "Dumont",
                "given": "Eric",
                "sequence": "additional"
            },
            {
                "affiliation": [
                    {
                        "name": "From St Paul\u2019s Hospital, University of British Columbia, Vancouver, British Columbia, Canada (J.G.W., D.A.W., J.Y., R.G., J.-B.M., R.G.C., N.W., F.N., M.J., C.R.T., R.M., J.L., B.M., S.V.L., A.C.); Quebec Heart and Lung Institute, Quebec City, Quebec, Canada (J.R.-C., E.D.); Toronto General Hospital, Toronto, Ontario, Canada (M.O., E.H.); and King\u2019s College Hospital, London, UK (O.W.)."
                    }
                ],
                "family": "Carere",
                "given": "Ronald G.",
                "sequence": "additional"
            },
            {
                "affiliation": [
                    {
                        "name": "From St Paul\u2019s Hospital, University of British Columbia, Vancouver, British Columbia, Canada (J.G.W., D.A.W., J.Y., R.G., J.-B.M., R.G.C., N.W., F.N., M.J., C.R.T., R.M., J.L., B.M., S.V.L., A.C.); Quebec Heart and Lung Institute, Quebec City, Quebec, Canada (J.R.-C., E.D.); Toronto General Hospital, Toronto, Ontario, Canada (M.O., E.H.); and King\u2019s College Hospital, London, UK (O.W.)."
                    }
                ],
                "family": "Wijesinghe",
                "given": "Namal",
                "sequence": "additional"
            },
            {
                "affiliation": [
                    {
                        "name": "From St Paul\u2019s Hospital, University of British Columbia, Vancouver, British Columbia, Canada (J.G.W., D.A.W., J.Y., R.G., J.-B.M., R.G.C., N.W., F.N., M.J., C.R.T., R.M., J.L., B.M., S.V.L., A.C.); Quebec Heart and Lung Institute, Quebec City, Quebec, Canada (J.R.-C., E.D.); Toronto General Hospital, Toronto, Ontario, Canada (M.O., E.H.); and King\u2019s College Hospital, London, UK (O.W.)."
                    }
                ],
                "family": "Nietlispach",
                "given": "Fabian",
                "sequence": "additional"
            },
            {
                "affiliation": [
                    {
                        "name": "From St Paul\u2019s Hospital, University of British Columbia, Vancouver, British Columbia, Canada (J.G.W., D.A.W., J.Y., R.G., J.-B.M., R.G.C., N.W., F.N., M.J., C.R.T., R.M., J.L., B.M., S.V.L., A.C.); Quebec Heart and Lung Institute, Quebec City, Quebec, Canada (J.R.-C., E.D.); Toronto General Hospital, Toronto, Ontario, Canada (M.O., E.H.); and King\u2019s College Hospital, London, UK (O.W.)."
                    }
                ],
                "family": "Johnson",
                "given": "Mark",
                "sequence": "additional"
            },
            {
                "affiliation": [
                    {
                        "name": "From St Paul\u2019s Hospital, University of British Columbia, Vancouver, British Columbia, Canada (J.G.W., D.A.W., J.Y., R.G., J.-B.M., R.G.C., N.W., F.N., M.J., C.R.T., R.M., J.L., B.M., S.V.L., A.C.); Quebec Heart and Lung Institute, Quebec City, Quebec, Canada (J.R.-C., E.D.); Toronto General Hospital, Toronto, Ontario, Canada (M.O., E.H.); and King\u2019s College Hospital, London, UK (O.W.)."
                    }
                ],
                "family": "Thompson",
                "given": "Chrisopher R.",
                "sequence": "additional"
            },
            {
                "affiliation": [
                    {
                        "name": "From St Paul\u2019s Hospital, University of British Columbia, Vancouver, British Columbia, Canada (J.G.W., D.A.W., J.Y., R.G., J.-B.M., R.G.C., N.W., F.N., M.J., C.R.T., R.M., J.L., B.M., S.V.L., A.C.); Quebec Heart and Lung Institute, Quebec City, Quebec, Canada (J.R.-C., E.D.); Toronto General Hospital, Toronto, Ontario, Canada (M.O., E.H.); and King\u2019s College Hospital, London, UK (O.W.)."
                    }
                ],
                "family": "Moss",
                "given": "Robert",
                "sequence": "additional"
            },
            {
                "affiliation": [
                    {
                        "name": "From St Paul\u2019s Hospital, University of British Columbia, Vancouver, British Columbia, Canada (J.G.W., D.A.W., J.Y., R.G., J.-B.M., R.G.C., N.W., F.N., M.J., C.R.T., R.M., J.L., B.M., S.V.L., A.C.); Quebec Heart and Lung Institute, Quebec City, Quebec, Canada (J.R.-C., E.D.); Toronto General Hospital, Toronto, Ontario, Canada (M.O., E.H.); and King\u2019s College Hospital, London, UK (O.W.)."
                    }
                ],
                "family": "Leipsic",
                "given": "Jonathon",
                "sequence": "additional"
            },
            {
                "affiliation": [
                    {
                        "name": "From St Paul\u2019s Hospital, University of British Columbia, Vancouver, British Columbia, Canada (J.G.W., D.A.W., J.Y., R.G., J.-B.M., R.G.C., N.W., F.N., M.J., C.R.T., R.M., J.L., B.M., S.V.L., A.C.); Quebec Heart and Lung Institute, Quebec City, Quebec, Canada (J.R.-C., E.D.); Toronto General Hospital, Toronto, Ontario, Canada (M.O., E.H.); and King\u2019s College Hospital, London, UK (O.W.)."
                    }
                ],
                "family": "Munt",
                "given": "Brad",
                "sequence": "additional"
            },
            {
                "affiliation": [
                    {
                        "name": "From St Paul\u2019s Hospital, University of British Columbia, Vancouver, British Columbia, Canada (J.G.W., D.A.W., J.Y., R.G., J.-B.M., R.G.C., N.W., F.N., M.J., C.R.T., R.M., J.L., B.M., S.V.L., A.C.); Quebec Heart and Lung Institute, Quebec City, Quebec, Canada (J.R.-C., E.D.); Toronto General Hospital, Toronto, Ontario, Canada (M.O., E.H.); and King\u2019s College Hospital, London, UK (O.W.)."
                    }
                ],
                "family": "Lichtenstein",
                "given": "Samuel V.",
                "sequence": "additional"
            },
            {
                "affiliation": [
                    {
                        "name": "From St Paul\u2019s Hospital, University of British Columbia, Vancouver, British Columbia, Canada (J.G.W., D.A.W., J.Y., R.G., J.-B.M., R.G.C., N.W., F.N., M.J., C.R.T., R.M., J.L., B.M., S.V.L., A.C.); Quebec Heart and Lung Institute, Quebec City, Quebec, Canada (J.R.-C., E.D.); Toronto General Hospital, Toronto, Ontario, Canada (M.O., E.H.); and King\u2019s College Hospital, London, UK (O.W.)."
                    }
                ],
                "family": "Cheung",
                "given": "Anson",
                "sequence": "additional"
            }
        ],
        "container-title": [
            "Circulation"
        ],
        "content-domain": {
            "crossmark-restriction": false,
            "domain": []
        },
        "created": {
            "date-parts": [
                [
                    2010,
                    4,
                    13
                ]
            ],
            "date-time": "2010-04-13T03:54:51Z",
            "timestamp": 1271130891000
        },
        "deposited": {
            "date-parts": [
                [
                    2018,
                    9,
                    30
                ]
            ],
            "date-time": "2018-09-30T19:08:41Z",
            "timestamp": 1538334521000
        },
        "indexed": {
            "date-parts": [
                [
                    2021,
                    3,
                    19
                ]
            ],
            "date-time": "2021-03-19T21:43:59Z",
            "timestamp": 1616190239297
        },
        "is-referenced-by-count": 376,
        "issn-type": [
            {
                "type": "print",
                "value": "0009-7322"
            },
            {
                "type": "electronic",
                "value": "1524-4539"
            }
        ],
        "issue": "16",
        "issued": {
            "date-parts": [
                [
                    2010,
                    4,
                    27
                ]
            ]
        },
        "journal-issue": {
            "issue": "16",
            "published-print": {
                "date-parts": [
                    [
                        2010,
                        4,
                        27
                    ]
                ]
            }
        },
        "language": "en",
        "member": "276",
        "page": "1848-1857",
        "prefix": "10.1161",
        "published-print": {
            "date-parts": [
                [
                    2010,
                    4,
                    27
                ]
            ]
        },
        "publisher": "Ovid Technologies (Wolters Kluwer Health)",
        "reference": [
            {
                "DOI": "10.1067/mtc.2001.116470",
                "doi-asserted-by": "publisher",
                "key": "e_1_3_2_1_2"
            },
            {
                "first-page": "256",
                "journal-title": "J Heart Valve Dis",
                "key": "e_1_3_2_2_2",
                "volume": "18",
                "year": "2009"
            },
            {
                "DOI": "10.1016/j.jacc.2008.03.036",
                "doi-asserted-by": "publisher",
                "key": "e_1_3_2_3_2"
            },
            {
                "DOI": "10.1016/j.jcin.2007.11.010",
                "doi-asserted-by": "publisher",
                "key": "e_1_3_2_4_2"
            },
            {
                "DOI": "10.1016/j.jacc.2007.03.030",
                "doi-asserted-by": "publisher",
                "key": "e_1_3_2_5_2"
            },
            {
                "DOI": "10.1002/ccd.21379",
                "doi-asserted-by": "publisher",
                "key": "e_1_3_2_6_2"
            },
            {
                "DOI": "10.1002/ccd.21300",
                "doi-asserted-by": "publisher",
                "key": "e_1_3_2_7_2"
            },
            {
                "DOI": "10.1016/j.athoracsur.2007.12.040",
                "doi-asserted-by": "publisher",
                "key": "e_1_3_2_8_2"
            },
            {
                "DOI": "10.1016/j.athoracsur.2008.10.016",
                "doi-asserted-by": "publisher",
                "key": "e_1_3_2_9_2"
            },
            {
                "DOI": "10.1002/ccd.21597",
                "doi-asserted-by": "publisher",
                "key": "e_1_3_2_10_2"
            },
            {
                "DOI": "10.1016/j.athoracsur.2009.02.053",
                "doi-asserted-by": "publisher",
                "key": "e_1_3_2_11_2"
            },
            {
                "DOI": "10.1002/ccd.22279",
                "doi-asserted-by": "publisher",
                "key": "e_1_3_2_12_2"
            },
            {
                "DOI": "10.1016/j.jtcvs.2009.07.081",
                "doi-asserted-by": "crossref",
                "key": "e_1_3_2_13_2",
                "unstructured": "Wong D Ye J Cheung A Webb JG Carere R Lichtenstein SV. Technical considerations to avoid pitfalls during transapical aortic valve implantation. J Thorac Cardiovasc Surg. January 30 2010. DOI: 10.1016/j.jtcvs.2009.07.081. Available at: http://www.sciencedirect.com. Accessed March 23 2010."
            },
            {
                "DOI": "10.1016/j.ejcts.2007.12.055",
                "doi-asserted-by": "publisher",
                "key": "e_1_3_2_14_2"
            },
            {
                "DOI": "10.1161/circulationaha.104.523266",
                "doi-asserted-by": "publisher",
                "key": "e_1_3_2_15_2"
            },
            {
                "DOI": "10.1016/S0735-1097(02)01822-3",
                "doi-asserted-by": "publisher",
                "key": "e_1_3_2_16_2"
            },
            {
                "DOI": "10.1002/ccd.20753",
                "doi-asserted-by": "publisher",
                "key": "e_1_3_2_17_2"
            },
            {
                "DOI": "10.1016/j.ejcts.2006.10.023",
                "doi-asserted-by": "publisher",
                "key": "e_1_3_2_18_2"
            },
            {
                "key": "e_1_3_2_19_2",
                "unstructured": "Rode\u0301s-Cabau J Dumont E Doyle D Lemieux J. Transcatheter valve-in-valve implantation for the treatment of stentless aortic valve dysfunction. J Thorac Cardiovas Surg. September 25 2009. DOI: 10.1016/j.jtcvs.2009.07.073. Available at: http://www.sciencedirect.com. Accessed March 23 2010."
            },
            {
                "DOI": "10.1016/j.jcmg.2008.04.003",
                "doi-asserted-by": "publisher",
                "key": "e_1_3_2_20_2"
            },
            {
                "DOI": "10.1016/j.jcin.2008.04.007",
                "doi-asserted-by": "publisher",
                "key": "e_1_3_2_21_2"
            },
            {
                "DOI": "10.1016/j.jcin.2009.07.005",
                "doi-asserted-by": "publisher",
                "key": "e_1_3_2_22_2"
            },
            {
                "first-page": "2382",
                "journal-title": "Eur Heart J",
                "key": "e_1_3_2_23_2",
                "volume": "29",
                "year": "2009"
            },
            {
                "DOI": "10.4244/EIJV4I3A63",
                "doi-asserted-by": "publisher",
                "key": "e_1_3_2_24_2"
            },
            {
                "DOI": "10.1016/j.jacc.2009.01.060",
                "doi-asserted-by": "publisher",
                "key": "e_1_3_2_25_2"
            },
            {
                "DOI": "10.1161/circulationaha.108.837807",
                "doi-asserted-by": "publisher",
                "key": "e_1_3_2_26_2"
            },
            {
                "DOI": "10.1016/j.jacc.2006.01.049",
                "doi-asserted-by": "publisher",
                "key": "e_1_3_2_27_2"
            },
            {
                "DOI": "10.1016/S0003-4975(98)00758-9",
                "doi-asserted-by": "publisher",
                "key": "e_1_3_2_28_2"
            },
            {
                "first-page": "206",
                "journal-title": "Interact Cardiovasc Thorac Surg",
                "key": "e_1_3_2_29_2",
                "volume": "8",
                "year": "2009"
            }
        ],
        "reference-count": 29,
        "references-count": 29,
        "relation": {
            "cites": []
        },
        "score": 17.458746,
        "short-container-title": [
            "Circulation"
        ],
        "source": "Crossref",
        "title": [
            "Transcatheter Valve-in-Valve Implantation for Failed Bioprosthetic Heart Valves"
        ],
        "type": "journal-article",
        "volume": "121"
    }
]